dim/__init__.py
dim/allocator.py
dim/autodns3.py
dim/cli.py
dim/commands.py
dim/crypto.py
dim/defaults.py
dim/dns.py
dim/errors.py
dim/ipaddr.py
dim/iptrie.py
dim/jsonrpc.py
dim/ldap_auth.py
dim/ldap_sync.py
dim/manage_db.py
dim/manage_dim.py
dim/messages.py
dim/report.py
dim/rpc.py
dim/rrtype.py
dim/transaction.py
dim/util.py
dim/version.py
dim/models/__init__.py
dim/models/dns.py
dim/models/history.py
dim/models/ip.py
dim/models/migrate.py
dim/models/rights.py
dim/models/schema.py
dim/models/util.py
dim/sql/migrate_1.0_to_2.sql
dim/sql/migrate_10_to_11.sql
dim/sql/migrate_11_to_12.sql
dim/sql/migrate_2_to_3.sql
dim/sql/migrate_3_to_4.sql
dim/sql/migrate_4_to_5.sql
dim/sql/migrate_5_to_6.sql
dim/sql/migrate_6_to_7.sql
dim/sql/migrate_7_to_8.sql
dim/sql/migrate_8_to_9.sql
dim/sql/migrate_9_to_10.sql
dim/sql/rollback_6_to_5.sql
dim/sql/rollback_8_to_7.sql
dim/sql/rollback_9_to_8.sql
dimserver-5.0.2rc2.data/scripts/manage_db
dimserver-5.0.2rc2.data/scripts/manage_dim
dimserver-5.0.2rc2.data/scripts/report
etc/dim.wsgi
etc/pool_report.template
dimserver-5.0.2rc2.dist-info/METADATA
dimserver-5.0.2rc2.dist-info/WHEEL
dimserver-5.0.2rc2.dist-info/entry_points.txt
dimserver-5.0.2rc2.dist-info/top_level.txt
dimserver-5.0.2rc2.dist-info/RECORD
