Metadata-Version: 2.1
Name: dimserver
Version: 5.0.2rc2
Summary: DNS and IP management Python server
Maintainer: zerimond
Project-URL: Homepage, https://github.com/ionos-cloud/dim
Project-URL: Issues, https://github.com/ionos-cloud/dim/issues
Classifier: Development Status :: 5 - Production/Stable
Classifier: Intended Audience :: Developers
Classifier: Programming Language :: Python :: 3
Classifier: License :: OSI Approved :: MIT License
Classifier: Operating System :: OS Independent
Requires-Python: >=3.9
Requires-Dist: mysqlclient >=1.4.6
Requires-Dist: SQLAlchemy ~=1.4
Requires-Dist: ldap3 ~=2.9
Requires-Dist: Flask ~=2.1
Requires-Dist: Flask-SQLAlchemy ~=2.5
Requires-Dist: Jinja2 ~=3.1
Requires-Dist: dnspython !=2.2.0,~=2.1
Requires-Dist: requests ~=2.27
Requires-Dist: pycryptodome ~=3.14
Requires-Dist: gunicorn >=21
Provides-Extra: docs
Requires-Dist: nose ~=1.3 ; extra == 'docs'
Requires-Dist: nose-ignore-docstring ~=0.2 ; extra == 'docs'
Requires-Dist: pytest ~=7.1 ; extra == 'docs'
Requires-Dist: pytest-cov ~=3.0 ; extra == 'docs'
Requires-Dist: Sphinx ~=4.4 ; extra == 'docs'
